README.rst
setup.py
ktorrent/__init__.py
ktorrent/ktorrent.py
ktorrent/test.py
ktorrent.egg-info/PKG-INFO
ktorrent.egg-info/SOURCES.txt
ktorrent.egg-info/dependency_links.txt
ktorrent.egg-info/requires.txt
ktorrent.egg-info/top_level.txt